<?xml version="1.0" encoding="UTF-8"?>
<objects serializationModel="Studio.02.02.00">
	<object class="AudioFile" id="{18563bbb-85d7-41c5-a1eb-1e3213d3eada}">
		<property name="assetPath">
			<value>Universal Sound FX/VOICES/Words_Phrases/Female/VOICE_FEMALE_You_Lose_2_mono.wav</value>
		</property>
		<property name="frequencyInKHz">
			<value>44.0999985</value>
		</property>
		<property name="channelCount">
			<value>1</value>
		</property>
		<property name="length">
			<value>1.1139002267573697</value>
		</property>
		<relationship name="masterAssetFolder">
			<destination>{1efee77c-6a9e-489e-bd69-3b4140aed501}</destination>
		</relationship>
	</object>
</objects>
