<?xml version="1.0" encoding="UTF-8"?>
<objects serializationModel="Studio.02.02.00">
	<object class="AudioFile" id="{18ee29e5-d685-4e6e-a3e3-eab3f1aa7f01}">
		<property name="assetPath">
			<value>Universal Sound FX/EXPLOSIONS/Medium/EXPLOSION_Medium_Implosion_with_Bright_Overlay_stereo.wav</value>
		</property>
		<property name="frequencyInKHz">
			<value>44.0999985</value>
		</property>
		<property name="channelCount">
			<value>2</value>
		</property>
		<property name="length">
			<value>1.9920634920634921</value>
		</property>
		<relationship name="masterAssetFolder">
			<destination>{1efee77c-6a9e-489e-bd69-3b4140aed501}</destination>
		</relationship>
	</object>
</objects>
