<?xml version="1.0" encoding="UTF-8"?>
<objects serializationModel="Studio.02.02.00">
	<object class="AudioFile" id="{5e7132db-01b0-452a-b82b-c8d3bc5f1838}">
		<property name="assetPath">
			<value>Universal Sound FX/FABRIC_CLOTHING/FABRIC_Flap_05_mono.wav</value>
		</property>
		<property name="frequencyInKHz">
			<value>44.0999985</value>
		</property>
		<property name="channelCount">
			<value>1</value>
		</property>
		<property name="length">
			<value>0.66839002267573699</value>
		</property>
		<relationship name="masterAssetFolder">
			<destination>{1efee77c-6a9e-489e-bd69-3b4140aed501}</destination>
		</relationship>
	</object>
</objects>
