<?xml version="1.0" encoding="UTF-8"?>
<objects serializationModel="Studio.02.02.00">
	<object class="AudioFile" id="{aac21466-f58e-4b6c-8702-bd6f1753bc7e}">
		<property name="assetPath">
			<value>Universal Sound FX/HUMAN/Footsteps/Leather_Wood_Hollow_Jog/FOOTSTEP_Leather_Wood_Hollow_Jog_RR5_mono.wav</value>
		</property>
		<property name="frequencyInKHz">
			<value>44.0999985</value>
		</property>
		<property name="channelCount">
			<value>1</value>
		</property>
		<property name="length">
			<value>0.42900226757369614</value>
		</property>
		<relationship name="masterAssetFolder">
			<destination>{1efee77c-6a9e-489e-bd69-3b4140aed501}</destination>
		</relationship>
	</object>
</objects>
