<?xml version="1.0" encoding="UTF-8"?>
<objects serializationModel="Studio.02.02.00">
	<object class="AudioFile" id="{c9658674-4575-4194-93b2-167b2b005100}">
		<property name="assetPath">
			<value>Universal Sound FX/IMPACTS/Punch/IMPACT_Punch_03_mono.wav</value>
		</property>
		<property name="frequencyInKHz">
			<value>44.0999985</value>
		</property>
		<property name="channelCount">
			<value>1</value>
		</property>
		<property name="length">
			<value>0.25911564625850342</value>
		</property>
		<relationship name="masterAssetFolder">
			<destination>{1efee77c-6a9e-489e-bd69-3b4140aed501}</destination>
		</relationship>
	</object>
</objects>
